<?xml version="1.0" encoding="UTF-8"?>
<exp:Export Version="3.0"
    xmlns:L7p="http://www.layer7tech.com/ws/policy"
    xmlns:exp="http://www.layer7tech.com/ws/policy/export" xmlns:wsp="http://schemas.xmlsoap.org/ws/2002/12/policy">
    <exp:References/>
    <wsp:Policy xmlns:L7p="http://www.layer7tech.com/ws/policy" xmlns:wsp="http://schemas.xmlsoap.org/ws/2002/12/policy">
        <wsp:All wsp:Usage="Required">
            <L7p:CommentAssertion>
                <L7p:Comment stringValue="This is an empty policy used only to show an example of storing a policy file in the Layer7-Community GitHub"/>
            </L7p:CommentAssertion>
        </wsp:All>
    </wsp:Policy>
</exp:Export>
